{
  "fieldLabels": {
    "acceptedTaxonName": {
      "name": {
        "en": "Accepted name"
      },
      "rank": {
        "en": "Accepted name rank"
      }
    },
    "curatorialName": {
      "en": "Curatorial taxon name",
      "sv": ""
    },
    "vernacularNames": {
      "name": {
        "en": "Vernacular names"
      }
    },
    "synonyms": {
      "name": {
        "en": "Synonyms"
      }
    },
    "parent": {
      "en": "parent",
      "acceptedTaxonName": {
        "name": {
          "en": "Parent accepted name"
        }
      }
    },
    "name": {
      "en": "Scientific name"
    },
    "taxonNameType": {
      "en": "Name type"
    },
    "rank": {
      "en": "Rank"
    },
    "rubinNumber": {
      "en": "RUBIN"
    },
    "class": {
      "en": "class"
    },
    "order": {
      "en": "order"
    },
    "family": {
      "en": "family"
    },
    "genus": {
      "en": "genus"
    },
    "species": {
      "en": "species"
    },
    "subspecies": {
      "en": "subspecies"
    }
  },
  "headers": {
    "connectedScientificNames": {
      "en": "connected scientific names",
      "sv": ""
    },
    "status": {
      "en": "status",
      "sv": ""
    },
    "newTaxon": {
      "en": "new taxon",
      "sv": ""
    },
    "newScientificName": {
      "en": "new scientific name",
      "sv": ""
    },
    "recordHistory": {
      "en": "Record history",
      "sv": ""
    },
    "vernacularNames": {
      "en": "vernacular names",
      "sv": ""
    }
  },
  "other": {
    "createdBy": {
      "en": "Created by",
      "sv": ""
    },
    "lastModifiedBy": {
      "en": "Last modified by",
      "sv": ""
    }
  },
  "acceptedNameForTaxon": {
    "en": "accepted name for taxon",
    "sv": ""
  },
  "addNameOrNames": {
    "en": "enter vernacular name(s)",
    "sv": ""
  },
  "addVernacularName": {
    "en": "add vernacular name",
    "sv": ""
  },
  "cancel": {
    "en": "Cancel",
    "sv": ""
  },
  "connectScientificName": {
    "en": "connect scientific name",
    "sv": ""
  },
  "name": {
    "en": "name"
  },
  "scientificNameOfRank": {
    "en": "Scientific name of rank",
    "sv": ""
  },
  "notAssociatedWithTaxon": {
    "en": "this name is not associated with any taxon",
    "sv": ""
  },
  "selectLanguage": {
    "en": "select language",
    "sv": ""
  },
  "synonymForTaxon": {
    "en": "synonym of",
    "sv": ""
  },
  "taxon": {
    "en": "taxon",
    "sv": ""
  },
  "save": {
    "en": "Save",
    "sv": "Spara"
  },
  "back": {
    "en": "Back",
    "sv": "Tillbaka"
  },
  "remove": {
    "en": "Remove",
    "sv": ""
  },
  "removeFromThisTaxon": {
    "en": "Remove from this taxon",
    "sv": ""
  },
  "removeThisTaxon": {
    "en": "Remove this taxon?",
    "sv": ""
  },
  "removeThisVernacularName": {
    "en": "Remove this vernacular name?",
    "sv": ""
  },
  "reset": {
    "en": "Reset",
    "sv": "Återställ"
  }
}
