{
  "data": {
    "type": "specimen",
    "relationships": {
      "places": {
        "data": [
          {
            "id": "1",
            "type": "place"
          },
          {
            "id": "2",
            "type": "place"
          },
          {
            "id": "3",
            "type": "place"
          },
          {
            "id": "4",
            "type": "place"
          },
          {
            "id": "5",
            "type": "place"
          }
        ]
      },
      "featureTypes": {
        "data": [
          {
            "id": "2",
            "type": "featureType"
          }
        ]
      },
      "physicalObjects": {
        "data": [
          {
            "id": "4234",
            "type": "physicalObject"
          }
        ]
      }
    },
    "attributes": {
      "publishRecord": true,
      "individual": {
        "collectionItems": [
          {
            "alternateIdentifiersText": "alternateIdentifiersText",
            "physicalObject": {
              "id": "2234",
              "type": "physicalObject"
            },
            "physicalObjectText": "physicalObjectText"
          }
        ],
        "determinations": [
          {
            "determinedByAgent": { "textV": "determinedByAgentText" },
            "remarks": "remarks"
          }
        ],
        "featureObservations": [
          {
            "featureObservationAgent": "featureObservationAgent",
            "featureObservationText": "21",
            "featureType": {
              "id": "1",
              "type": "featureType"
            },
            "methodText": "methodText"
          }
        ],
        "identifiers": [
          {
            "identifierType": { "id": "1", "type": "identifierType" },

            "namespace": "",
            "remarks": "",
            "value": "123456"
          }
        ],
        "collectingInformation": [
          {
            "collectorsText": "collectorsText",
            "event": {
              "dateRange": {
                "endDate": {
                  "dateText": "endDate"
                }
              },
              "expeditionText": "expeditionText",
              "locationInformation": {
                "coordinatesVerbatim": "coordinatesVerbatim",
                "places": [
                  {
                    "id": "1",
                    "type": "place"
                  },
                  {
                    "id": "2",
                    "type": "place"
                  },
                  {
                    "id": "3",
                    "type": "place"
                  },
                  {
                    "id": "4",
                    "type": "place"
                  },
                  {
                    "id": "5",
                    "type": "place"
                  }
                ],
                "georeferenceSourcesText": "georeferenceSourcesText",
                "localityV": "localityV",
                "position": {
                  "geodeticDatum": "geodeticDatum text",
                  "latitude": "latitude-string",
                  "longitude": "longitude-string",
                  "uncertaintyInMeters": 10
                },
                "remarks": "remarks",
                "verticalPosition": {
                  "maximumDepthInMeters": 100,
                  "maximumElevationInMeters": 100,
                  "minimumDepthInMeters": 20,
                  "minimumElevationInMeters": 20
                }
              }
            }
          }
        ]
      }
    }
  }
}
