{
  "enums": {
    "featureObservations": {
      "age": {
        "en": "Age",
        "sv": "Ålder"
      },
      "ageDeterminationMethod": {
        "en": "Age determination method",
        "sv": "Åldersbestämningsmetod"
      },
      "age-development-stage": {
        "en": "Age and development",
        "sv": ""
      },
      "age-in-years": {
        "en": "age in years",
        "sv": ""
      },
      "stage": {
        "en": "stage",
        "sv": ""
      },
      "age-stage": {
        "en": "life stage",
        "sv": "Åldersstadium"
      },
      "ageStage": {
        "en": "Age stage",
        "sv": "Åldersstadium"
      },
      "bone-count": {
        "en": "Bone counts",
        "sv": "Benantal"
      },
      "carcass-condition": {
        "en": "Carcass condition",
        "sv": "Tillstånd"
      },
      "conditionAtCollecting": {
        "en": "Condition at collecting",
        "sv": "Tillstånd vid insamling"
      },
      "length": {
        "en": "Lengths",
        "sv": "Längder"
      },
      "sex": {
        "en": "Sex",
        "sv": "Kön"
      },
      "stage-and-age": {
        "en": "Stage and age",
        "sv": "Stadium och ålder"
      },
      "weight": {
        "en": "Weights",
        "sv": "Vikter"
      }
    }
  },
  "fieldLabels": {
    "acquisition": {
      "acquisitionTypeText": {
        "en": "Acquisition type"
      },
      "date": {
        "en": "Acquisition date"
      },
      "handedInByAgent": {
        "en": "Interpreted name or agent",
        "textV": {
          "en": "Handed in by (stated)"
        }
      }
    },
    "collectingInformation": {
      "collectedByAgent": {
        "en": "Interpreted name or agent",
        "textV": {
          "en": "Collected by (stated)"
        }
      },
      "collectorsText": {
        "en": "Collected by (stated)"
      },
      "establishmentMeansType": {
        "en": "Establishment means"
      },
      "isDeathDate": {
        "en": "Died when collected",
        "sv": ""
      }
    },
    "collectionItems": {
      "description": {
        "en": "Description",
        "sv": "Beskrivning"
      },
      "preparationType": {
        "en": "Preparation type"
      },
      "remarks": {
        "en": "Preparation remarks"
      }
    },
    "curatorialAssessment": {
      "agent": {
        "en": "Assessed by (agent)"
      },
      "assessedByAgentT": {
        "en": "Assessed by (interpreted)"
      },
      "agentText": {
        "en": "Agent text"
      },
      "condition": {
        "en": "condition"
      },
      "conditionRemarks": {
        "en": "condition remarks"
      },
      "date": {
        "en": "date"
      },
      "isInStorage": {
        "en": "is in storage"
      },
      "isNotInStorage": {
        "en": "not in storage"
      },
      "inventoryStatusRemarks": {
        "en": "remarks"
      },
      "remarks": {
        "en": "Assessment remarks"
      }
    },
    "deathInformation": {
      "causeOfDeathType": {
        "en": "Cause of death"
      },
      "remarks": {
        "en": "Remarks"
      },
      "deathDetails": {
        "en": "Death details"
      },
      "diedAtColleting": {
        "en": "Died at collecting",
        "sv": ""
      }
    },
    "determinations": {
      "date": {
        "en": "Determination date"
      },
      "determinedByAgent": {
        "en": "Interpreted name or agent",
        "textV": {
          "en": "Determined by (stated)"
        }
      },
      "taxonNameI": {
        "en": "Interpreted taxon name"
      },
      "taxonNameV": {
        "en": "Determined as (stated)"
      },
      "remarks": {
        "en": "Determination remarks"
      }
    },
    "event": {
      "expeditionText": {
        "en": "Expedition"
      },
      "dateRange": {
        "en": "date",
        "sv": ""
      },

      "remarks": {
        "en": "Remarks"
      },
      "readOnly": {
        "en": "Read only"
      }
    },
    "features": {
      "age": {
        "en": "age in years",
        "sv": ""
      },
      "age-stage": {
        "en": "stage",
        "sv": ""
      },
      "sex": {
        "en": "sex",
        "sv": ""
      },
      "carcass-condition": {
        "en": "condition",
        "sv": ""
      },
      "cranium-count": {
        "en": "cranium count",
        "sv": ""
      },
      "mandibula-count": {
        "en": "mandibula count",
        "sv": ""
      },
      "vertebrae-count": {
        "en": "vertebrae count",
        "sv": ""
      },
      "costae-count": {
        "en": "costae count",
        "sv": ""
      },
      "scapula-count": {
        "en": "scapula count",
        "sv": ""
      },
      "humerus-count": {
        "en": "humerus count",
        "sv": ""
      },
      "ulna-count": {
        "en": "ulna count",
        "sv": ""
      },
      "radius-count": {
        "en": "radius count",
        "sv": ""
      },
      "manus-count": {
        "en": "manus count",
        "sv": ""
      },
      "pelvis-count": {
        "en": "pelvis count",
        "sv": ""
      },
      "femur-count": {
        "en": "femur count",
        "sv": ""
      },
      "tibia-count": {
        "en": "tibia count",
        "sv": ""
      },
      "pedis-count": {
        "en": "pedis count",
        "sv": ""
      },
      "bacculum-count": {
        "en": "bacculum count",
        "sv": ""
      },
      "complete-body-weight": {
        "en": "Complete body",
        "sv": ""
      },
      "skinned-weight": {
        "en": "skinned",
        "sv": ""
      },
      "gutted-weight": {
        "en": "gutted",
        "sv": ""
      },
      "slaughtered-weight": {
        "en": "slaughtered",
        "sv": ""
      },
      "unknown-weight-type": {
        "en": "other",
        "sv": ""
      },
      "total-length": {
        "en": "total length",
        "sv": ""
      },
      "body-length": {
        "en": "body length",
        "sv": ""
      },
      "tail-to-anus-length": {
        "en": "tail-anus length",
        "sv": ""
      },
      "tail-to-pelvis-length": {
        "en": "tail-pelvis length",
        "sv": ""
      },
      "ear-length": {
        "en": "ear length",
        "sv": ""
      },
      "hind-foot-length": {
        "en": "hind-foot length",
        "sv": ""
      }
    },
    "individual": {
      "causeOfDeathStandardized": {
        "en": "Cause of death",
        "sv": ""
      },
      "causeOfDeathText": {
        "en": "Death remark",
        "sv": ""
      },
      "originStandardized": {
        "en": "Origin",
        "sv": ""
      },
      "collectionItemText": {
        "en": "Collection item Text"
      },
      "remarks": {
        "en": "Remarks"
      }
    },
    "legacyData": {
      "en": "Legacy data"
    },
    "locationInformation": {
      "coordinatesVerbatim": {
        "en": "Coordinate (stated)",
        "sv": ""
      },
      "localityV": {
        "en": "Stated locality",
        "sv": "Angiven (verbatim) lokalitet"
      },
      "localityI": {
        "en": "Interpreted locality",
        "sv": ""
      },
      "swedishGrid5km": {
        "en": "RT90 Index 5km",
        "sv": ""
      },
      "localityRemarks": {
        "en": "Locality remarks",
        "sv": "Lokalitetsnoteringar"
      },
      "remarks": {
        "en": "Locality remarks"
      },
      "readOnly": {
        "en": "Read only"
      },
      "georeferenceSourcesText": {
        "en": "Georeference sources"
      },
      "places": {
        "en": "Higher geography",
        "sv": ""
      }
    },
    "originInformation": {
      "isResultOfSelectiveBreeding": {
        "en": "Result of selective breeding"
      },
      "isAffectedByManagement": {
        "en": "Affected by management"
      },
      "originLocality": {
        "en": "Origin locality",
        "sv": ""
      },
      "remarks": {
        "en": "Remarks",
        "sv": ""
      }
    },
    "physicalObject": {
      "storageLocation": {
        "en": "Normal storage location",
        "sv": ""
      }
    },
    "places": {
      "choose": {
        "en": "Choose...",
        "sv": "Välj..."
      },
      "higherGeography": {
        "en": "Higher geography"
      },
      "swedishMap": {
        "en": "Swedish map"
      }
    },
    "position": {
      "uncertaintyInMeters": {
        "en": "Uncertainty estimate (m)",
        "sv": ""
      },
      "geodeticDatum": {
        "en": "Geodetic datum",
        "sv": "Geodetiskt datum"
      },
      "latitude": {
        "en": "Latitude",
        "sv": "Latitud (N)"
      },
      "longitude": {
        "en": "Longitude",
        "sv": "Longitud (E)"
      },
      "referenceSystem": {
        "en": "Reference system"
      }
    },
    "recordHistoryEvents": {
      "agent": {
        "en": "card author",
        "sv": ""
      },
      "date": {
        "en": "card date",
        "sv": ""
      }
    },
    "specimen": {
      "publishRecord": {
        "en": "Public",
        "sv": "Publikt"
      },
      "remarks": {
        "en": "remarks"
      },
      "readOnly": {
        "en": "Read only"
      }
    },
    "taxonInformation": {
      "curatorialTaxon": {
        "en": "Taxon name"
      },
      "readOnly": {
        "en": "Read only"
      },
      "taxonRemarks": {
        "en": "Taxon remarks"
      },
      "typeStatus": {
        "en": "Type status",
        "sv": "Typstatus"
      },
      "typifiedName": {
        "en": "Typified name",
        "sv": ""
      },
      "oldScientificName": {
        "en": "Old scientific name"
      },
      "oldLocalName": {
        "en": "Old local name"
      }
    },
    "verticalPosition": {
      "maximumDepthInMeters": {
        "en": "Depth max (m)",
        "sv": "Max"
      },
      "maximumElevationInMeters": {
        "en": "Elevation max (m)",
        "sv": "Max"
      },
      "minimumDepthInMeters": {
        "en": "Depth min (m)",
        "sv": "Min"
      },
      "minimumElevationInMeters": {
        "en": "Elevation min (m)",
        "sv": "Min"
      }
    }
  },
  "headers": {
    "acquisition": {
      "en": "acquisition",
      "sv": ""
    },
    "basicInformation": {
      "en": "Specimen basics",
      "sv": ""
    },
    "collectingDate": {
      "en": "collecting date",
      "sv": ""
    },
    "collectingAndDeathDetails": {
      "en": "collecting and death",
      "sv": ""
    },
    "collectorAndExpedition": {
      "en": "Collector and expedition"
    },
    "collectingInformation": {
      "en": "collecting information"
    },
    "death": {
      "en": "Death",
      "sv": ""
    },
    "collectingLocality": {
      "en": "collecting locality"
    },
    "curatorialAssessments": {
      "en": "Curatorial assessments",
      "sv": ""
    },
    "determinations": {
      "en": "determinations"
    },
    "editCuratorialAssessment": {
      "en": "Edit curatorial assessment",
      "sv": ""
    },
    "externalEvents": {
      "en": "external events",
      "sv": ""
    },
    "features": {
      "en": "Features"
    },
    "identifiers": {
      "en": "identifiers",
      "sv": ""
    },
    "legacyData": {
      "en": "Legacy data"
    },
    "localityOrigin": {
      "en": "locality and origin"
    },
    "localityPosition": {
      "en": "Position of collecting locality",
      "sv": ""
    },
    "newSpecimen": {
      "en": "New specimen",
      "sv": "Nytt exemplar"
    },
    "origin": {
      "en": "origin",
      "sv": ""
    },
    "physicalObjects": {
      "en": "physical objects",
      "otherPreparation": {
        "en": "other preparations",
        "sv": ""
      },
      "skeleton": {
        "en": "skeletons",
        "sv": ""
      },
      "skin": {
        "en": "skins",
        "sv": ""
      },
      "wetPreparation": {
        "en": "wet preparations",
        "sv": ""
      }
    },
    "recordHistory": {
      "en": "record history",
      "sv": ""
    },
    "taxon": {
      "en": "taxon"
    },
    "taxonomy": {
      "en": "taxonomy",
      "sv": ""
    },
    "taxonPreferredName": {
      "en": "taxon name (preferred)",
      "sv": ""
    },
    "taxonOtherNames": {
      "en": "additional names",
      "sv": ""
    },
    "typeInformation": {
      "en": "Type information",
      "sv": ""
    }
  },
  "helpTexts": {
    "locationInformation": {
      "localityI": {
        "en":
          "Locality name(s) which don’t fit to other fields. E.g. detailed place or water body (e.g. “Frescati” or “Baltic sea”)",
        "sv": ""
      },
      "remarks": {
        "en": "Notes on the locality",
        "sv": ""
      }
    },
    "position": {
      "latitude": {
        "en":
          "Latitude or northing. Use negative number or letter S for coordinates on southern hemisphere.",
        "sv": ""
      },
      "longitude": {
        "en":
          "Longitude or easting. Use negative number or letter W for coordinates on western hemisphere.",
        "sv": ""
      },
      "uncertaintyInMeters": {
        "en": "Uncertainty (m)"
      }
    },
    "verticalPosition": {
      "maximumDepthInMeters": {
        "en":
          "If you fill in one, you have to fill in the other also. Use “?” for unknown data",
        "sv": ""
      },
      "maximumElevationInMeters": {
        "en":
          "If you fill in one, you have to fill in the other also. Use “?” for unknown data",
        "sv": ""
      },
      "minimumDepthInMeters": {
        "en":
          "If you fill in one, you have to fill in the other also. Use “?” for unknown data",
        "sv": ""
      },
      "minimumElevationInMeters": {
        "en":
          "If you fill in one, you have to fill in the other also. Use “?” for unknown data",
        "sv": ""
      }
    }
  },
  "filterTitles": {
    "identifier": {
      "en": "Catalog number/identifier",
      "sv": ""
    },
    "taxonomy": {
      "en": "Taxonomy",
      "sv": ""
    },
    "locality": {
      "en": "Locality and origin",
      "sv": ""
    },
    "datePeriod": {
      "en": "Collecting date",
      "sv": ""
    },
    "agent": {
      "en": "Agent/name",
      "sv": ""
    },
    "physicalObject": {
      "en": "Preparation type",
      "sv": ""
    },
    "storage": {
      "en": "Storage",
      "sv": ""
    },
    "ageAndStage": {
      "en": "Age and development",
      "sv": ""
    },
    "sex": {
      "en": "Sex",
      "sv": ""
    },
    "bones": {
      "en": "Bones",
      "sv": ""
    },
    "weight": {
      "en": "Weight",
      "sv": ""
    },
    "length": {
      "en": "Length",
      "sv": ""
    },
    "collectingCondition": {
      "en": "Carcass condition",
      "sv": ""
    }
  },
  "tableColumns": {
    "identifiersCatalogNumber": {
      "en": "Catalog no.",
      "sv": ""
    },
    "taxonomyCuratorialName": {
      "en": "Taxon",
      "sv": ""
    },
    "taxonomyRank": {
      "en": "taxon rank",
      "sv": ""
    },
    "taxonomyFamily": {
      "en": "family",
      "sv": ""
    },
    "taxonomyGenus": {
      "en": "genus",
      "sv": ""
    },
    "taxonomySpecies": {
      "en": "species",
      "sv": ""
    },
    "taxonomySubspecies": {
      "en": "subspecies",
      "sv": ""
    },
    "collectingEventCollectors": {
      "en": "collector",
      "sv": ""
    },
    "nomenclaturalTypeTypeStatus": {
      "en": "type status",
      "sv": ""
    },
    "collectingEventStartDate": {
      "en": "collecting start",
      "sv": ""
    },
    "collectingEventEndDate": {
      "en": "collecting end",
      "sv": ""
    },
    "collectingEventLocality": {
      "en": "stated locality (collecting)",
      "sv": ""
    },
    "collectingEventInterpretedLocality": {
      "en": "interpreted locality (collecting)",
      "sv": ""
    },
    "collectingEventCountry": {
      "en": "country (collecting)",
      "sv": ""
    },
    "collectingEventProvince": {
      "en": "province (collecting)",
      "sv": ""
    },
    "collectingEventDistrict": {
      "en": "district (collecting)",
      "sv": ""
    },
    "originInformationLocality": {
      "en": "locality (origin)",
      "sv": ""
    },
    "deathInformationDeath": {
      "en": "death",
      "sv": ""
    },
    "physicalUnitSkeleton": {
      "en": "skeleton",
      "sv": ""
    },
    "physicalUnitSkin": {
      "en": "skin",
      "sv": ""
    },
    "physicalUnitWetPreparation": {
      "en": "wet preparation",
      "sv": ""
    },
    "physicalUnitOtherPreparation": {
      "en": "other preparation",
      "sv": ""
    },
    "featureSex": {
      "en": "sex",
      "sv": ""
    },
    "featureAgeStage": {
      "en": "stage",
      "sv": ""
    },
    "featureAge": {
      "en": "age",
      "sv": ""
    },
    "featureCompleteBodyWeight": {
      "en": "complete weight",
      "sv": ""
    },
    "featureTotalLength": {
      "en": "total length",
      "sv": ""
    },
    "featureBodyLength": {
      "en": "body length",
      "sv": ""
    },
    "featureCondition": {
      "en": "carcass condition",
      "sv": ""
    },
    "identifiersOtherIdentifiers": {
      "en": "identifiers",
      "sv": ""
    },
    "recordEventCataloged": {
      "en": "cataloged",
      "sv": ""
    },
    "recordEventRegistered": {
      "en": "registered",
      "sv": ""
    },
    "recordEventLastModified": {
      "en": "last modified",
      "sv": ""
    }
  },
  "formSectionTitles": {
    "basicInformation": {
      "en": "Specimen basics",
      "sv": ""
    },
    "taxonomy": {
      "en": "Taxonomy",
      "sv": ""
    },
    "localityOrigin": {
      "en": "Locality and origin",
      "sv": ""
    },
    "collectingDeath": {
      "en": "Collecting and death",
      "sv": ""
    },
    "features": {
      "en": "Features",
      "sv": ""
    },
    "physicalObjects": {
      "en": "Physical objects",
      "sv": ""
    },
    "summary": {
      "en": "Summary",
      "sv": ""
    }
  },
  "formSectionDescriptions": {
    "basicInformation": {
      "en": "Identifiers, acquisition and record history",
      "sv": ""
    },
    "taxonomy": {
      "en": "Taxon name, type info, determination",
      "sv": ""
    },
    "localityOrigin": {
      "en": "Collecting locality, origin and breeding",
      "sv": ""
    },
    "collectingDeath": {
      "en": "Collector, expedition, date and death details",
      "sv": ""
    },
    "features": {
      "en": "Age, sex, condition, measurements and bones",
      "sv": ""
    },
    "physicalObjects": {
      "en": "Skin, skeleton, wet and other preparations",
      "sv": ""
    },
    "summary": {
      "en": "Summary of all data about the specimen",
      "sv": ""
    }
  },
  "identifierType": {
    "en": "Identifier type"
  },
  "value": {
    "en": "Value"
  },
  "remarks": {
    "emptyState": {
      "acquisition": {
        "en": "add acquisition remarks...",
        "sv": ""
      },
      "collectionItems": {
        "en": "add remarks for all objects...",
        "sv": ""
      },
      "death": {
        "en": "add death remars...",
        "sv": ""
      },
      "date": {
        "en": "add date remarks...",
        "sv": ""
      },
      "determination": {
        "en": "add determination remarks...",
        "sv": ""
      },
      "collectingLocationRemarks": {
        "en": "Add collecting locality remarks...",
        "sv": ""
      },
      "origin": {
        "en": "Add origin remarks...",
        "sv": ""
      },
      "physicalObject": {
        "skeleton": {
          "en": "add remarks for this skeleton...",
          "sv": ""
        },
        "skin": {
          "en": "add remarks for this skin...",
          "sv": ""
        },
        "wet-preparation": {
          "en": "add remarks for this wet preparation...",
          "sv": ""
        },
        "other-preparation": {
          "en": "add remarks for this other preparation..."
        }
      },
      "specimen": {
        "en": "add remarks for the entire specimen...",
        "sv": ""
      },
      "taxonomy": {
        "en": "Add taxonomy remarks..."
      }
    },
    "resultPrefix": {
      "acquisition": {
        "en": "acquisition remarks",
        "sv": ""
      },
      "date": {
        "en": "date remarks",
        "sv": ""
      },
      "death": {
        "en": "death remarks",
        "sv": ""
      },
      "collectingLocationRemarks": {
        "en": "collecting locality remarks",
        "sv": ""
      },
      "origin": {
        "en": "origin remarks",
        "sv": ""
      },
      "physicalObjects": {
        "en": "physical objects remarks",
        "sv": ""
      },
      "specimen": {
        "en": "specimen remarks",
        "sv": ""
      },
      "taxonomy": {
        "en": "taxonomy remarks",
        "sv": ""
      }
    },
    "en": "Remarks"
  },
  "remove": {
    "en": "Delete"
  },
  "skeleton": {
    "en": "skeleton"
  },

  "featureObservations": {
    "placeholders": {
      "age": {
        "en": "Add age",
        "sv": ""
      },
      "age-stage": {
        "en": "Select stage",
        "sv": ""
      },
      "sex": {
        "en": "Select sex",
        "sv": ""
      },
      "carcass-condition": {
        "en": "Select carcass condition",
        "sv": ""
      },
      "weight": {
        "en": "Add weight",
        "sv": ""
      },
      "length": {
        "en": "Add length",
        "sv": ""
      },
      "selectMethod": {
        "en": "Select method",
        "sv": ""
      },
      "selectUnit": {
        "en": "Select unit",
        "sv": ""
      }
    },
    "other": {
      "age": {
        "en": "Age in years"
      },
      "age-stage": {
        "en": "Development stage"
      },
      "sex": {
        "en": "Sex",
        "sv": ""
      },
      "complete-body-weight": {
        "en": "Complete"
      },
      "skinned-weight": {
        "en": "Skinned"
      },
      "gutted-weight": {
        "en": "Gutted"
      },
      "slaughtered-weight": {
        "en": "Slaughtered"
      },
      "unknown-weight-type": {
        "en": "Other"
      },
      "total-length": {
        "en": "Total"
      },
      "body-length": {
        "en": "Body"
      },
      "tail-to-anus-length": {
        "en": "Tail-anus"
      },
      "tail-to-pelvis-length": {
        "en": "Tail-pelvis"
      },
      "ear-length": {
        "en": "Ear"
      },
      "hind-foot-length": {
        "en": "Hind-foot"
      },
      "carcass-condition": {
        "en": "Condition"
      },
      "cranium-count": {
        "en": "Cranium",
        "sv": ""
      },
      "mandibula-count": {
        "en": "Mandibula",
        "sv": ""
      },
      "vertebrae-count": {
        "en": "Vertebrae",
        "sv": ""
      },
      "costae-count": {
        "en": "Costae",
        "sv": ""
      },
      "scapula-count": {
        "en": "Scapula",
        "sv": ""
      },
      "humerus-count": {
        "en": "Humerus",
        "sv": ""
      },
      "ulna-count": {
        "en": "Ulna",
        "sv": ""
      },
      "radius-count": {
        "en": "Radius",
        "sv": ""
      },
      "manus-count": {
        "en": "Manus",
        "sv": ""
      },
      "pelvis-count": {
        "en": "Pelvis",
        "sv": ""
      },
      "femur-count": {
        "en": "Femur",
        "sv": ""
      },
      "tibia-count": {
        "en": "Tibia",
        "sv": ""
      },
      "pedis-count": {
        "en": "Pedis",
        "sv": ""
      },
      "bacculum-count": {
        "en": "Bacculum",
        "sv": ""
      }
    }
  },
  "recordHistoryEvent": {
    "recordedByAgentT": {
      "en": "Recorded by (stated)"
    },
    "recordedByAgentN": {
      "en": "Recorded by (interpreted)"
    }
  },
  "other": {
    "add": {
      "en": "Add",
      "sv": "Lägg till"
    },
    "addAcquisition": {
      "en": "add acquisition",
      "sv": ""
    },
    "addAgent": {
      "en": "add agent/name",
      "sv": ""
    },
    "interpretThisName": {
      "en": "interpret this name",
      "sv": ""
    },
    "addCatalogCardCreation": {
      "en": "Add catalog card creation",
      "sv": ""
    },
    "addCatalogCardInformation": {
      "en": "Catalog card information",
      "sv": ""
    },
    "addCatalogNumber": {
      "en": "Add catalog number",
      "sv": "Lägg till katalognummer"
    },
    "addIdentifierOrIdentifiers": {
      "en": "add identifier(s)",
      "sv": ""
    },
    "addNameOrNames": {
      "en": "add name(s)",
      "sv": ""
    },
    "addOtherName": {
      "en": "Add additional name",
      "sv": ""
    },
    "addTypeStatus": {
      "en": "Add type information",
      "sv": ""
    },
    "addDetermination": {
      "en": "Add determination",
      "sv": "Lägg till bestämning"
    },
    "addIdentifier": {
      "en": "Add identifier",
      "sv": "Lägg till identifierare"
    },
    "addPosition": {
      "en": "Add position",
      "sv": ""
    },
    "addOrigin": {
      "en": "Add origin",
      "sv": ""
    },
    "agent": {
      "en": "Observed by (agent)"
    },
    "appearanceAtCollecting": {
      "en": "Appearance at the collecting locality",
      "sv": ""
    },
    "appearanceAtOrigin": {
      "en": "Appearance at the origin locality",
      "sv": ""
    },
    "by": {
      "en": "by",
      "sv": ""
    },
    "catalogCard": {
      "en": "Catalog card",
      "sv": "Katalogkort"
    },
    "catalogCardBy": {
      "en": "catalog card by",
      "sv": ""
    },
    "catalogNumber": {
      "en": "Catalog number",
      "sv": "Katalognummer"
    },
    "cancel": {
      "en": "Cancel",
      "sv": "Avbryt"
    },
    "createdBy": {
      "en": "Created by",
      "sv": ""
    },
    "createNewSpecimen": {
      "en": "Creating a new specimen record",
      "sv": ""
    },
    "coordinates": {
      "en": "Coordinate (interpreted, decimal degrees WGS84)"
    },
    "depth": {
      "en": "Depth min / max (m)",
      "sv": ""
    },
    "elevation": {
      "en": "Elevation min / max (m)",
      "sv": ""
    },
    "back": {
      "en": "Back",
      "sv": ""
    },
    "clearSearchParameters": {
      "en": "Clear search parameters",
      "sv": "Rensa sökparametrar"
    },
    "copy": {
      "en": "Copy",
      "sv": "Kopiera"
    },
    "copyToVerbatim": {
      "en": "Copy to determined as",
      "sv": "Kopiera till verbatim"
    },
    "choose": {
      "en": "Choose...",
      "sv": "Välj..."
    },
    "createdBy": {
      "en": "Created by",
      "sv": "Skapat av"
    },
    "date": {
      "en": "Date"
    },
    "done": {
      "en": "Done",
      "sv": ""
    },
    "edit": {
      "en": "Edit",
      "sv": "Redigera"
    },
    "editCatalogNumber": {
      "en": "Edit catalog number",
      "sv": "Redigera katalognummer"
    },
    "editCuratorialAssessment": {
      "en": "Edit curatorial assessment",
      "sv": ""
    },
    "formContainsErrors": {
      "en": "Form contains errors",
      "sv": "Formuläret innehåller fel"
    },
    "id": {
      "en": "id"
    },
    "lastModifiedBy": {
      "en": "Last modified by",
      "sv": ""
    },
    "latitude": {
      "en": "Latitude",
      "sv": ""
    },
    "longitude": {
      "en": "Longitude",
      "sv": ""
    },
    "loading": {
      "en": "loading",
      "sv": "laddar"
    },
    "method": {
      "en": "Method",
      "sv": "Metod"
    },
    "physicalObjects": {
      "addSkeleton": {
        "en": "Add a skeleton",
        "sv": ""
      },
      "addSkin": {
        "en": "Add a skin",
        "sv": ""
      },
      "addWetPreparation": {
        "en": "Add a wet preparation",
        "sv": ""
      },
      "addOtherPreparation": {
        "en": "Add an other preparation",
        "sv": ""
      },
      "removeSkeleton": {
        "en": "Delete this skeleton?",
        "sv": ""
      },
      "removeSkin": {
        "en": "Delete this skin?",
        "sv": ""
      },
      "removeWetPreparation": {
        "en": "Delete this wet preparation?",
        "sv": ""
      },
      "removeOtherPreparation": {
        "en": "Delete this other preparation?",
        "sv": ""
      },
      "deleteSkeleton": {
        "en": "Delete skeleton",
        "sv": ""
      },
      "deleteSkin": {
        "en": "Delete skin",
        "sv": ""
      },
      "deleteWetPreparation": {
        "en": "Delete wet preparation",
        "sv": ""
      },
      "deleteOtherPreparation": {
        "en": "Delete other preparation",
        "sv": ""
      }
    },
    "newAssessment": {
      "en": "New assessment",
      "sv": ""
    },
    "newCuratorialAssessment": {
      "en": "New curatorial assessment",
      "sv": ""
    },
    "noRecordsFound": {
      "en": "No matching records found",
      "sv": "Inga matchande utdrag funna"
    },
    "remarks": {
      "en": "Remarks"
    },
    "deleteDetermination": {
      "en": "Delete determination",
      "sv": ""
    },
    "remove": {
      "en": "Delete",
      "sv": "Ta bort"
    },
    "removeThisCuratorialAssessment": {
      "en": "Delete this curatorial assessment?",
      "sv": ""
    },
    "removeThisDetermination": {
      "en": "Delete this determination?",
      "sv": ""
    },
    "removeThisIdentifier": {
      "en": "Delete this identifier?",
      "sv": ""
    },
    "removeThisPhysicalObjects": {
      "en": "Delete this physical object?",
      "sv": ""
    },
    "removeThisOtherName": {
      "en": "Delete this name?",
      "sv": ""
    },
    "reset": {
      "en": "Reset",
      "sv": "Återställ"
    },
    "saveChanges": {
      "en": "Save changes",
      "sv": "Spara ändringar"
    },
    "save": {
      "en": "Save",
      "sv": "Spara"
    },
    "saved": {
      "en": "Saved",
      "sv": "Sparat"
    },
    "search": {
      "en": "Search",
      "sv": "Sök"
    },
    "selectIdentifierType": {
      "en": "select identifier type",
      "sv": ""
    },
    "selectKindOfName": {
      "en": "select kind of name",
      "sv": ""
    },
    "selectiveBreeding": {
      "en": "Has the animal been affected by selective breeding?",
      "sv": ""
    },
    "wildAnimal": {
      "en": "No (wild animal)",
      "sv": ""
    },
    "zooAnimal": {
      "en": "Yes (zoo animal or similar)",
      "sv": ""
    },
    "unknown": {
      "en": "unknown",
      "sv": ""
    },
    "sixOrEightDigits": {
      "en": "6 or 8 digits",
      "sv": "6 eller 8 siffror"
    },
    "useThisNumber": {
      "en": "Use this number",
      "sv": ""
    },
    "automaticCatalogNumber": {
      "en": "Would you like an automatic catalog number for this specimen?",
      "sv": ""
    },
    "yesCreateNumber": {
      "en": "Yes, create a number",
      "sv": ""
    },
    "enterManully": {
      "en": "No, I will enter one manually",
      "sv": ""
    },
    "submitFailed": {
      "en": "Could not save",
      "sv": "Kunde inte spara"
    },
    "unit": {
      "en": "Unit",
      "sv": "Enhet"
    },
    "value": {
      "en": "Value",
      "sv": "Värde"
    },
    "weight": {
      "en": "Weights",
      "sv": "Vikter"
    }
  },
  "duplicate": {
    "en": "this catalog number is already registered",
    "sv": ""
  }
}
